smartifyLLM/__init__.py
smartifyLLM/advanced_finance.py
smartifyLLM/prompts.py
smartifyLLM/quick_rag.py
smartifyLLM/smart_llm.py
smartifyLLM/text_splitter.py
smartifyLLM/web_tools.py
smartifyllm-0.1.1.dist-info/licenses/LICENSE
smartifyllm-0.1.1.dist-info/METADATA
smartifyllm-0.1.1.dist-info/WHEEL
smartifyllm-0.1.1.dist-info/top_level.txt
smartifyllm-0.1.1.dist-info/RECORD
