Metadata-Version: 2.4
Name: smartifyLLM
Version: 0.1.1
Summary: A package that enhances local LLMs with real-time web awareness and adaptive context retrieval, making them smarter with no retraining or fine-tuning.
Author: Rajdeep Roshan Sahu
License: MIT
Requires-Python: >=3.9
License-File: LICENSE
Requires-Dist: torch==2.6.0
Requires-Dist: python-docx==1.1.2
Requires-Dist: pdfplumber==0.11.5
Requires-Dist: beautifulsoup4==4.13.3
Requires-Dist: fake-useragent==2.1.0
Requires-Dist: sentence_transformers==3.4.1
Requires-Dist: numpy==1.26.4
Requires-Dist: requests==2.32.3
Requires-Dist: yfinance==0.2.55
Dynamic: license-file
